Products.Flash10Fix-configure.zcml
README.txt
setup.py
Products/__init__.py
Products.Flash10Fix.egg-info/PKG-INFO
Products.Flash10Fix.egg-info/SOURCES.txt
Products.Flash10Fix.egg-info/dependency_links.txt
Products.Flash10Fix.egg-info/entry_points.txt
Products.Flash10Fix.egg-info/namespace_packages.txt
Products.Flash10Fix.egg-info/not-zip-safe
Products.Flash10Fix.egg-info/requires.txt
Products.Flash10Fix.egg-info/top_level.txt
Products/Flash10Fix/__init__.py
Products/Flash10Fix/configure.zcml
docs/HISTORY.txt