Metadata-Version: 1.0
Name: Products.Flash10Fix
Version: 1.0
Summary: This package fixes http://dev.plone.org/plone/ticket/8624 which prevents .swf movies from playing in Flash 10 when served from Plone.
Home-page: UNKNOWN
Author: David Glick
Author-email: davidglick@onenw.org
License: GPL
Keywords: plone flash video swf
Platform: UNKNOWN
Classifier: Programming Language :: Python
Classifier: Topic :: Software Development :: Libraries :: Python Modules
Classifier: Framework :: Plone
